README.md
setup.py
pulumi_vco/__init__.py
pulumi_vco/_utilities.py
pulumi_vco/provider.py
pulumi_vco/pulumi-plugin.json
pulumi_vco/py.typed
pulumi_vco.egg-info/PKG-INFO
pulumi_vco.egg-info/SOURCES.txt
pulumi_vco.egg-info/dependency_links.txt
pulumi_vco.egg-info/not-zip-safe
pulumi_vco.egg-info/requires.txt
pulumi_vco.egg-info/top_level.txt
pulumi_vco/anti_affinity_group/__init__.py
pulumi_vco/anti_affinity_group/anti_affinity_group_vm.py
pulumi_vco/base/__init__.py
pulumi_vco/base/cloudspace.py
pulumi_vco/base/disk.py
pulumi_vco/base/object_space.py
pulumi_vco/cloudspace/__init__.py
pulumi_vco/cloudspace/anti_affinity_group.py
pulumi_vco/cloudspace/connected_cloudspace.py
pulumi_vco/cloudspace/external_network.py
pulumi_vco/cloudspace/outputs.py
pulumi_vco/cloudspace/port_forward.py
pulumi_vco/cloudspace/virtual_machine.py
pulumi_vco/disk/__init__.py
pulumi_vco/disk/exposed_disk.py
pulumi_vco/disk/outputs.py
pulumi_vco/ingress/__init__.py
pulumi_vco/ingress/host.py
pulumi_vco/ingress/load_balancer.py
pulumi_vco/ingress/outputs.py
pulumi_vco/ingress/reverse_proxy.py
pulumi_vco/ingress/server_pool.py
pulumi_vco/objectspace/__init__.py
pulumi_vco/objectspace/link.py
pulumi_vco/virtual_machine/__init__.py
pulumi_vco/virtual_machine/virtual_machine_cd.py
pulumi_vco/virtual_machine/virtual_machine_disk.py
pulumi_vco/virtual_machine/virtual_machine_nic.py