Metadata-Version: 2.1
Name: pulumi-vco
Version: 0.0.39
Summary: The Whitesky.Cloud Vco Provider for Pulumi enables you to manipulate resources in the vco portal.
Home-page: https://whitesky.cloud/
Project-URL: Repository, https://github.com/fabianv-cloud/pulumi-vco-native
Keywords: whitesky.cloud pulumi vco category/utility kind/native
Requires-Python: >=3.7
